odoo/addons/l10n_ee_reporting/README.rst
odoo/addons/l10n_ee_reporting/__init__.py
odoo/addons/l10n_ee_reporting/__manifest__.py
odoo/addons/l10n_ee_reporting/hooks.py
odoo/addons/l10n_ee_reporting/data/balance_sheet.xml
odoo/addons/l10n_ee_reporting/data/income_statement.xml
odoo/addons/l10n_ee_reporting/data/kmd_2017.xml
odoo/addons/l10n_ee_reporting/i18n/l10n_ee_reporting.pot
odoo/addons/l10n_ee_reporting/models/__init__.py
odoo/addons/l10n_ee_reporting/models/l10n_ee_reporting_kmd_inf.py
odoo/addons/l10n_ee_reporting/models/l10n_ee_reporting_vies_declaration.py
odoo/addons/l10n_ee_reporting/readme/CONTRIBUTORS.rst
odoo/addons/l10n_ee_reporting/readme/DESCRIPTION.rst
odoo/addons/l10n_ee_reporting/security/ir.model.access.csv
odoo/addons/l10n_ee_reporting/security/l10n_ee_reporting_security.xml
odoo/addons/l10n_ee_reporting/static/description/icon.png
odoo/addons/l10n_ee_reporting/static/description/index.html
odoo/addons/l10n_ee_reporting/views/l10n_ee_reporting.xml
odoo/addons/l10n_ee_reporting/views/l10n_ee_reporting_kmd_inf.xml
odoo/addons/l10n_ee_reporting/views/l10n_ee_reporting_vies_declaration.xml
odoo_addon_l10n_ee_reporting-15.0.1.2.1.1.dist-info/METADATA
odoo_addon_l10n_ee_reporting-15.0.1.2.1.1.dist-info/WHEEL
odoo_addon_l10n_ee_reporting-15.0.1.2.1.1.dist-info/top_level.txt
odoo_addon_l10n_ee_reporting-15.0.1.2.1.1.dist-info/RECORD
