Metadata-Version: 2.1
Name: odoo-addon-l10n-ee-reporting
Version: 15.0.1.2.1.1
Summary: Estonian reporting localization
Home-page: https://github.com/OCA/l10n-estonia
Author: CorporateHub, Cetmix, Odoo Community Association (OCA)
Author-email: support@odoo-community.org
License: AGPL-3
Platform: UNKNOWN
Classifier: Programming Language :: Python
Classifier: Framework :: Odoo
Classifier: Framework :: Odoo :: 15.0
Classifier: License :: OSI Approved :: GNU Affero General Public License v3
Requires-Python: >=3.8
Requires-Dist: odoo-addon-l10n-ee-accounting <15.1dev,>=15.0dev
Requires-Dist: odoo-addon-mis-builder <15.1dev,>=15.0dev
Requires-Dist: odoo <15.1dev,>=15.0a
